<xml xmlns="https://developers.google.com/blockly/xml"><block type="component_event" id="~R(iOJ|4ul=d6i6c:`V]" x="415" y="216"><mutation xmlns="http://www.w3.org/1999/xhtml" component_name="camera" component_type="Button" parent_id="undefined" event_id="Click" was_updated="true"></mutation><field name="component_id">1eac5547-5cc9-46d7-a370-b1e94e06f896</field><field name="event_id">Click</field><statement name="input_do"><block type="controls_if" id="E(.YHeFC@heq;hpLQ4Y5"><value name="IF0"><block type="set_get" id="x7BA7sGBD~Kmb:]C0A!+"><mutation xmlns="http://www.w3.org/1999/xhtml" component_name="voiceSwitch" parent_id="undefined"></mutation><field name="component_id">be4074dd-721e-452e-b3fe-1c03e73f2d06</field><field name="field_name">value</field></block></value><statement name="DO0"><block type="speech_speak_text" id="{HaT3xj]@3aEHIv-z)f?"><value name="TEXT"><shadow type="text" id="D{2rk.I*}}l)hywV2IjJ"><field name="TEXT">Picture Taken</field></shadow></value><value name="LANGUAGE"><shadow type="device_language" id=";E7m[EFNnhnE1=Jbwohf"><mutation xmlns="http://www.w3.org/1999/xhtml" parent_block_name="speech_speak_text"></mutation><field name="LANGUAGE">en-US</field></shadow></value></block></statement><next><block type="setter" id="s!3o-o?E%.[WCq8%KYFD"><mutation xmlns="http://www.w3.org/1999/xhtml" component_name="Image1" parent_id="undefined"></mutation><field name="component_id">58ff4b6b-d9de-482c-8ccb-d1fa81b28b62</field><field name="field_name">Picture</field><value name="field_value"><shadow type="asset_get" id=";(iII1FODmL:I}Ymy[nk"><mutation xmlns="http://www.w3.org/1999/xhtml" previous_asset_name="" previous_asset_value="INVALID_ASSET"></mutation><field name="ASSET">INVALID_ASSET</field></shadow><block type="camera_take_photo" id="YQv3d6z_g@oI|`.uw8{-"></block></value></block></next></block></statement></block><block type="component_event" id="T~cRat?D@E0;qrHW0mcu" x="414" y="374"><mutation xmlns="http://www.w3.org/1999/xhtml" component_name="photo library" component_type="Button" parent_id="undefined" event_id="Click" was_updated="true"></mutation><field name="component_id">f8dc1ffb-5c00-4ab8-ba57-91f9f3552c2d</field><field name="event_id">Click</field><statement name="input_do"><block type="setter" id="eljVrMAjNIYjpu]b4q37"><mutation xmlns="http://www.w3.org/1999/xhtml" component_name="Image1" parent_id="undefined"></mutation><field name="component_id">58ff4b6b-d9de-482c-8ccb-d1fa81b28b62</field><field name="field_name">Picture</field><value name="field_value"><shadow type="asset_get" id="!GK|NNM$Y49@=TDlp;/G"><mutation xmlns="http://www.w3.org/1999/xhtml" previous_asset_name="" previous_asset_value="INVALID_ASSET"></mutation><field name="ASSET">INVALID_ASSET</field></shadow><block type="camera_select_photo" id="oK9+KRC-ZJ4~xq|JQCb5"><field name="MEDIA_TYPE_OPTIONS">PHOTO</field></block></value></block></statement></block><block type="component_event" id="c~9XM,i:*/uthE(c@(R7" x="411" y="448"><mutation xmlns="http://www.w3.org/1999/xhtml" component_name="describe" component_type="Button" parent_id="undefined" event_id="Click" was_updated="true"></mutation><field name="component_id">654b8815-6179-43d1-923e-f8253967404c</field><field name="event_id">Click</field><statement name="input_do"><block type="setter" id="[m,WRcRUcW`|+[jHoqL2"><mutation xmlns="http://www.w3.org/1999/xhtml" component_name="Description Label" parent_id="undefined"></mutation><field name="component_id">f25e184d-d3e9-41e7-8e37-f2aa19e78860</field><field name="field_name">Text</field><value name="field_value"><shadow type="text" id="}Q8[{I,.{F_sjIf@H(rG"><field name="TEXT">Label</field></shadow><block type="camera_describe_image" id="E4(FYo-gE0VDM;L-4T?9"><value name="IMAGE"><shadow type="camera_take_photo" id="`{:f9oJ:Vjt^.0{vW[m}"></shadow><block type="set_get" id="yjV?#S[v+kM]{)(VG(85"><mutation xmlns="http://www.w3.org/1999/xhtml" component_name="Image1" parent_id="undefined"></mutation><field name="component_id">58ff4b6b-d9de-482c-8ccb-d1fa81b28b62</field><field name="field_name">Picture</field></block></value></block></value></block></statement></block><block type="component_event" id="|gN%v[6OH2C@rV?w5-ya" x="408" y="537"><mutation xmlns="http://www.w3.org/1999/xhtml" component_name="scan" component_type="Button" parent_id="undefined" event_id="Click" was_updated="true"></mutation><field name="component_id">fd852159-ce52-4431-8ff2-661cd00280ec</field><field name="event_id">Click</field><statement name="input_do"><block type="setter" id="WtxRwit#-uapfYyv|IJH"><mutation xmlns="http://www.w3.org/1999/xhtml" component_name="Description Label" parent_id="undefined"></mutation><field name="component_id">f25e184d-d3e9-41e7-8e37-f2aa19e78860</field><field name="field_name">Text</field><value name="field_value"><shadow type="text" id="pPNa1{e2!!v^ysvT!|Y4"><field name="TEXT">Label</field></shadow><block type="camera_scan_barcode" id="@Vc_@w`(B20.kz^.1Y{Z"><field name="CAMERA_OPTIONS">back</field></block></value></block></statement></block><block type="component_event" id="J6vh.%sp_L=_LN+/HSla" x="405" y="621"><mutation xmlns="http://www.w3.org/1999/xhtml" component_name="upload" component_type="Button" parent_id="undefined" event_id="Click" was_updated="true"></mutation><field name="component_id">4e2ab742-3e4a-4372-ae16-2eb3f3580a0d</field><field name="event_id">Click</field><statement name="input_do"><block type="setter" id="p}o9)w)MeVV#4_6X7Wx["><mutation xmlns="http://www.w3.org/1999/xhtml" component_name="Description Label" parent_id="undefined"></mutation><field name="component_id">f25e184d-d3e9-41e7-8e37-f2aa19e78860</field><field name="field_name">Text</field><value name="field_value"><shadow type="text" id="(c$6$d;`p$iX-0h`jV)x"><field name="TEXT">Label</field></shadow><block type="camera_upload_image" id="5G[t~*ZxkpskWn)a^kPa"><value name="IMAGE"><shadow type="asset_get" id="3mq#d7eI}3o^{rU6O)aS"><mutation xmlns="http://www.w3.org/1999/xhtml" previous_asset_name="" previous_asset_value="INVALID_ASSET"></mutation><field name="ASSET">INVALID_ASSET</field></shadow><block type="set_get" id="SR^CGM}Vt.-jgZ8:flxK"><mutation xmlns="http://www.w3.org/1999/xhtml" component_name="Image1" parent_id="undefined"></mutation><field name="component_id">58ff4b6b-d9de-482c-8ccb-d1fa81b28b62</field><field name="field_name">Picture</field></block></value></block></value></block></statement></block></xml>